dettag/__init__.py
dettag/best.pt
dettag/detect.py
dettag/gan_generator.h5
dettag-1.1.1.dist-info/METADATA
dettag-1.1.1.dist-info/WHEEL
dettag-1.1.1.dist-info/licenses/LICENSE
dettag-1.1.1.dist-info/RECORD
