Metadata-Version: 2.1
Name: dettag
Version: 1.1.1
Summary: For detection of tags in PIDs
Project-URL: Homepage, https://github.com/pypa/sampleproject
Project-URL: Bug Tracker, https://github.com/jithamanyu001/DetTag.git/issues
License-File: LICENSE
Classifier: License :: OSI Approved :: MIT License
Classifier: Operating System :: OS Independent
Classifier: Programming Language :: Python :: 3
Requires-Python: >=3.7
Requires-Dist: matplotlib!=3.6.1,>=3.3
Requires-Dist: numpy!=1.24.0,>=1.20
Requires-Dist: opencv-python
Requires-Dist: paddleocr
Requires-Dist: paddlepaddle
Requires-Dist: pandas>=1.2
Requires-Dist: seaborn
Requires-Dist: tensorflow
Requires-Dist: torch
Provides-Extra: dev
Requires-Dist: flake8; extra == 'dev'
Requires-Dist: flit; extra == 'dev'
Requires-Dist: mypy; extra == 'dev'
Requires-Dist: pandas-stubs; extra == 'dev'
Requires-Dist: pre-commit; extra == 'dev'
Requires-Dist: pytest; extra == 'dev'
Requires-Dist: pytest-cov; extra == 'dev'
Requires-Dist: pytest-xdist; extra == 'dev'
Provides-Extra: docs
Requires-Dist: ipykernel; extra == 'docs'
Requires-Dist: nbconvert; extra == 'docs'
Requires-Dist: numpydoc; extra == 'docs'
Requires-Dist: pydata-sphinx-theme==0.10.0rc2; extra == 'docs'
Requires-Dist: pyyaml; extra == 'docs'
Requires-Dist: sphinx-copybutton; extra == 'docs'
Requires-Dist: sphinx-design; extra == 'docs'
Requires-Dist: sphinx-issues; extra == 'docs'
Provides-Extra: stats
Requires-Dist: scipy>=1.7; extra == 'stats'
Requires-Dist: statsmodels>=0.12; extra == 'stats'
